Bioplots/__init__.py
Bioplots/cluster.py
Bioplots/distribution.py
Bioplots/utils.py
Bioplots/data/datasets.csv
Bioplots-0.1.6.9.dist-info/LICENSE
Bioplots-0.1.6.9.dist-info/METADATA
Bioplots-0.1.6.9.dist-info/WHEEL
Bioplots-0.1.6.9.dist-info/top_level.txt
Bioplots-0.1.6.9.dist-info/RECORD
