Metadata-Version: 2.1
Name: Bioplots
Version: 0.1.6.9
Summary: A data visualization package for bioinformatians and computational biologist
Home-page: https://jingxinfu.github.io/Bioplots
Author: Jingxin Fu
Author-email: jingxinfu.tj@gmail.com
License: UNKNOWN
Keywords: Data Visualization,Bioinformatics,Genomics,Computational Biologist
Platform: UNKNOWN
Classifier: Programming Language :: Python :: 3
Classifier: License :: OSI Approved :: GNU General Public License v3 or later (GPLv3+)
Classifier: Operating System :: Unix
Classifier: Operating System :: MacOS
Requires-Python: >=3, <4
Requires-Dist: pandas (>=0.24)
Requires-Dist: numpy
Requires-Dist: scipy
Requires-Dist: matplotlib
Requires-Dist: adjustText
